a_pandas_ex_apply_against_all/LICENSE
a_pandas_ex_apply_against_all/README.MD
a_pandas_ex_apply_against_all/__init__.py
a_pandas_ex_apply_against_all/requirements.txt
a_pandas_ex_apply_against_all/thirdparty.json
a_pandas_ex_apply_against_all-0.12.dist-info/LICENSE.rst
a_pandas_ex_apply_against_all-0.12.dist-info/METADATA
a_pandas_ex_apply_against_all-0.12.dist-info/WHEEL
a_pandas_ex_apply_against_all-0.12.dist-info/top_level.txt
a_pandas_ex_apply_against_all-0.12.dist-info/RECORD
